{
  "BTC": {
    "asset": "btc",
    "date": "2019-08-19T09:00:00+00:00",
    "epoch": 1566205200,
    "sentiment": -0.02982241217908773,
    "category": "Neutral"
  },
  "ETH": {
    "asset": "eth",
    "date": "2019-08-19T09:00:00+00:00",
    "epoch": 1566205200,
    "sentiment": -0.015154559365658979,
    "category": "Neutral"
  },
  "XRP": {
    "asset": "xrp",
    "date": "2019-08-19T09:00:00+00:00",
    "epoch": 1566205200,
    "sentiment": -0.008314264615100072,
    "category": "Neutral"
  },
  "LTC": {
    "asset": "ltc",
    "date": "2019-08-19T09:00:00+00:00",
    "epoch": 1566205200,
    "sentiment": 0.15261074836440763,
    "category": "Neutral"
  },
  "EOS": {
    "asset": "eos",
    "date": "2019-08-19T09:00:00+00:00",
    "epoch": 1566205200,
    "sentiment": 0.07036767626233313,
    "category": "Neutral"
  },
  "BCH": {
    "asset": "bch",
    "date": "2019-08-19T09:00:00+00:00",
    "epoch": 1566205200,
    "sentiment": 0.09719869659397447,
    "category": "Neutral"
  }
}